curiouslearner/__init__.py
curiouslearner/__main__.py
curiouslearner-0.0.1.dist-info/METADATA
curiouslearner-0.0.1.dist-info/RECORD
curiouslearner-0.0.1.dist-info/WHEEL
curiouslearner-0.0.1.dist-info/top_level.txt
